FSM_Implementation_Verilog/Verilog_Project/alu.v
module alu(input [7:0] A, 
input [7:0] B, 
input [3:0] ALU_Sel, 
output [7:0] ALU_Out, 
output CarryOut); // Carry Out Flag

    wire [7:0] ALU_Result;
    wire [8:0] tmp;

    assign ALU_Out = ALU_Result;
    assign tmp = {1'b0,A} + {1'b0,B};
    assign CarryOut = tmp[8]; // Carryout flag
    
    always @(*)   
        case(ALU_Sel)
        4'b0000: 
           ALU_Result = A + B ; 
        4'b0001: 
           ALU_Result = A - B ;
        4'b0010:
           ALU_Result = A * B;
        4'b0011: 
           ALU_Result = A/B;
        4'b0100: 
           ALU_Result = A<<1;
         4'b0101:
           ALU_Result = A>>1;
         4'b0110: 
           ALU_Result = {A[6:0],A[7]};
         4'b0111:
           ALU_Result = {A[0],A[7:1]};
          4'b1000:
           ALU_Result = A & B;
          4'b1001: 
           ALU_Result = A | B;
          4'b1010: 
           ALU_Result = A ^ B;
          4'b1011:
           ALU_Result = ~(A | B);
          4'b1100:
           ALU_Result = ~(A & B);
          4'b1101: 
           ALU_Result = ~(A ^ B);
          4'b1110: 
           ALU_Result = (A>B)?8'd1:8'd0 ;
          4'b1111: 
            ALU_Result = (A==B)?8'd1:8'd0 ;
          default: ALU_Result = A + B ; 
        endcase
endmodule


`timescale 1ns / 1ps  
module tb_alu;
  reg [7:0] A;
  reg [7:0] B;
  reg [3:0] ALU_Sel;
  wire [7:0] ALU_Out;
  wire CarryOut;
  
  alu test_uut (
    .A(A),
    .B(B),
    .ALU_Sel(ALU_Sel),
    .ALU_Out(ALU_Out),
    .CarryOut(CarryOut)
  );
  
  integer i;
  
  initial begin
    $dumpfile("alua.vcd");
    $dumpvars(0, test_uut);
    A = 8'h0A;
    B = 8'h02;
    ALU_Sel = 4'h0;
    
    for (i = 0; i < 16; i = i + 1) begin
      #10;
      ALU_Sel = ALU_Sel + 1;
    end
    
    A = 8'hF6;
    B = 8'h0A;
    
    #100 $finish;
  end
endmodule

FSM_Implementation_Verilog/Verilog_Project/alua.vcd
$date
	Fri Feb 17 10:30:02 2023
$end
$version
	Icarus Verilog
$end
$timescale
	1ps
$end
$scope module tb_alu $end
$scope module test_uut $end
$var wire 8 ! A [7:0] $end
$var wire 8 " ALU_Out [7:0] $end
$var wire 4 # ALU_Sel [3:0] $end
$var wire 8 $ B [7:0] $end
$var wire 9 % tmp [8:0] $end
$var wire 1 & CarryOut $end
$var reg 8 ' ALU_Result [7:0] $end
$upscope $end
$upscope $end
$enddefinitions $end
$comment Show the parameter values. $end
$dumpall
$end
#0
$dumpvars
b1000 '
0&
b1100 %
b10 $
b1 #
b1000 "
b1010 !
$end
#10000
b10100 "
b10100 '
b10 #
#20000
b101 "
b101 '
b11 #
#30000
b10100 "
b10100 '
b100 #
#40000
b101 "
b101 '
b101 #
#50000
b10100 "
b10100 '
b110 #
#60000
b101 "
b101 '
b111 #
#70000
b10 "
b10 '
b1000 #
#80000
b1010 "
b1010 '
b1001 #
#90000
b1000 "
b1000 '
b1010 #
#100000
b11110101 "
b11110101 '
b1011 #
#110000
b11111101 "
b11111101 '
b1100 #
#120000
b11110111 "
b11110111 '
b1101 #
#130000
b1 "
b1 '
b1110 #
#140000
b0 "
b0 '
b1111 #
#150000
b1100 "
b1100 '
b0 #
#160000
1&
b0 "
b0 '
b1010 $
b100000000 %
b11110110 !
