FSM_Implementation_Verilog/Verilog_Project/IMT2022543_fsm.v
module FSM( 
input clock, reset, inpt,
output reg outpt,
output reg[1:0] present_state);
parameter A=2'b01, B=2'b10, C=2'b11;
   
always @(clock,reset) 
begin
	if (reset) 
    begin
        present_state <= A;
        outpt <= 0;
    end
    else
    begin
        case (present_state)

        A :begin
            present_state=inpt?C:B;
            outpt <= 0;
        end

        B : begin
            present_state = inpt ? C : B;
            outpt <= inpt;
        end
        C : begin
            present_state = inpt ? C : B;
            outpt <= ~inpt;
        end
        endcase
    end
end
endmodule

`timescale 1ns/1ps
module FSM_tb();

    reg clock, reset, inpt;
    wire outpt; wire [1:0] present_state;
    FSM uut(clock, reset, inpt, outpt, present_state);

    initial 
    begin
        $dumpfile("FSM_tb.vcd");
        $dumpvars(0,FSM_tb);
        clock = 1;
	reset=1;
        inpt = 0;       #4;//at state B
        reset = 1;      #4;//at state A
        reset = 0;      #4;
        inpt = 0;       #4;// at state B
        inpt = 1;       #4;//at state C
        inpt = 1;       #4;//at state C
        inpt = 0;       #4;//at state B

        reset = 1;      #4;//at state A
        inpt = 1;       #4;//at state C
        reset = 0;      #4;
        inpt = 0;       #4;//at state B
        inpt = 0;       #4;//at state B
        inpt = 1;       #4;//at state C
    
    $finish;
    end

    always 
    begin
    #4 clock = ~clock;
    end
endmodule

FSM_Implementation_Verilog/Verilog_Project/FSM_tb.vcd
$date
	Fri Feb 17 14:33:42 2023
$end
$version
	Icarus Verilog
$end
$timescale
	1ps
$end
$scope module FSM_tb $end
$var wire 2 ! present_state [1:0] $end
$var wire 1 " outpt $end
$var reg 1 # clock $end
$var reg 1 $ inpt $end
$var reg 1 % reset $end
$scope module uut $end
$var wire 1 # clock $end
$var wire 1 $ inpt $end
$var wire 1 % reset $end
$var parameter 2 & A $end
$var parameter 2 ' B $end
$var parameter 2 ( C $end
$var reg 1 " outpt $end
$var reg 2 ) present_state [1:0] $end
$upscope $end
$upscope $end
$enddefinitions $end
$comment Show the parameter values. $end
$dumpall
b11 (
b10 '
b1 &
$end
#0
$dumpvars
b1 )
1%
0$
1#
0"
b1 !
$end
#4000
0#
#8000
b10 !
b10 )
1#
0%
#12000
0#
#16000
1"
b11 !
b11 )
1#
1$
#20000
0"
0#
#24000
1"
b10 !
b10 )
1#
0$
#28000
0"
b1 !
b1 )
0#
1%
#32000
1#
1$
#36000
b11 !
b11 )
0#
0%
#40000
1"
b10 !
b10 )
1#
0$
#44000
0"
0#
#48000
1"
b11 !
b11 )
1#
1$
#52000
0"
0#
