FSM_Implementation_Verilog/Verilog_Project/Another-Implementation-of-FSM.v
module FSM(clk, reset, in, out, present_state);
	input clk, reset, in;
	output reg out;
	output reg[1:0] present_state;
	localparam A=2'b00, B=2'b01, C=2'b10;
	
		
	always @ (negedge reset, posedge clk)
		if (reset) begin
		present_state <= A;
		out <= 0;
		end
		else       
		case (present_state)
			A :  if (in) begin
				present_state <= C;
				out <= 0;
				end
			    else begin
			     	present_state <= B;
			     	out <= 0;
			     	end
			B :  if (in) begin
				present_state <= C;
				out <= 1;
				end
			     else begin
			     	present_state <= B;
			     	out <= 0;
			     	end
			C :  if (in) begin 
				present_state <= C;
				out <= 0;
				end
			     else begin
			     	present_state <= B;
			     	out <= 1;
			     	end


    //As there are only three states one must be don't care term
		endcase
endmodule

`timescale 1ns/1ps
module testbench();
reg clk,reset,in;
wire out;

wire [1:0] present_state;

FSM dut(clk, reset, in, out, present_state);

initial begin
	$dumpfile("testbench.vcd");
	$dumpvars(0,testbench);
    clk = 1;
    reset = 1;
    in = 0;
    #5 reset = 0;
    #4 in = 1;
    #4 in = 0;
    #4 in = 1;
    #5 in = 0;
    reset = 1;
    #5 in = 1;
    reset = 0;
    #4 in = 0;
    #4 in = 1;
    #4 in = 0;
    #5
    
    $finish;
  end

  always #2 clk = ~clk;
endmodule

FSM_Implementation_Verilog/Verilog_Project/testbench.vcd
$date
	Fri Feb 17 12:00:51 2023
$end
$version
	Icarus Verilog
$end
$timescale
	1ps
$end
$scope module testbench $end
$var wire 2 ! present_state [1:0] $end
$var wire 1 " out $end
$var reg 1 # clk $end
$var reg 1 $ in $end
$var reg 1 % reset $end
$scope module dut $end
$var wire 1 # clk $end
$var wire 1 $ in $end
$var wire 1 % reset $end
$var parameter 2 & A $end
$var parameter 2 ' B $end
$var parameter 2 ( C $end
$var reg 1 " out $end
$var reg 2 ) present_state [1:0] $end
$upscope $end
$upscope $end
$enddefinitions $end
$comment Show the parameter values. $end
$dumpall
b10 (
b1 '
b0 &
$end
#0
$dumpvars
b0 )
1%
0$
1#
0"
b0 !
$end
#2000
0#
#4000
1#
#5000
b1 !
b1 )
0%
#6000
0#
#8000
1#
#9000
0"
b10 !
b10 )
1$
#10000
0#
#12000
1#
#13000
0"
b1 !
b1 )
0$
#14000
0#
#16000
1#
#17000
0"
b10 !
b10 )
1$
#18000
0#
#20000
1#
#22000
b0 !
b0 )
0#
1%
0$
#24000
1#
#26000
0#
#27000
b10 !
b10 )
0%
1$
#28000
1#
#30000
0#
#31000
0"
b1 !
b1 )
0$
#32000
1#
#34000
0#
#35000
0"
b10 !
b10 )
1$
#36000
1#
#38000
0#
#39000
0"
b1 !
b1 )
0$
