FSM_Implementation_Verilog/Verilog_Project/half_sub_incomplete.v
// add inputs, outputs
// add logic for gates in the assign statements 

module xor_gate(a,b,out);
input a,b;
output out;

assign out = ~a&b | a&~b;
endmodule


module and_gate(a,b,out);
input a,b;
output out;

assign out = a & b;
endmodule


module not_gate(a,out);
input a;
output out;

assign out = ~a;
endmodule


module half_subtractor(a, b, difference, borrow);
input a,b;
output difference, borrow;
wire x;

not_gate not_gate_in_half_sub(a,x);
xor_gate xor_gate_in_half_sub(a,b,difference);
and_gate and_gate_in_half_sub(x,b,borrow);
endmodule


//Testbench for half subtractor has been given
`timescale 1ns/1ps
module top;
 reg  A, B;
 wire Difference, Borrow; 
  half_subtractor instantiation(A, B, Difference, Borrow);
  initial
    begin
      $dumpfile("xyz.vcd");
      $dumpvars(0, top);
      A=0;
      B=0;
      #100 $finish;
    end

always #10 A=~A;
always #5 B=~B;
endmodule


// Error 1:
/*

half_sub_incomplete.v:27: error: reg out; cannot be driven by primitives or continuous assignment.
half_sub_incomplete.v:18: error: reg out; cannot be driven by primitives or continuous assignment.
half_sub_incomplete.v:9: error: reg out; cannot be driven by primitives or continuous assignment.
3 error(s) during elaboration.

Initially i did this in all the modules:
reg out;
assign out = a & b;

What I thought I was doing was (Becuase I thought since we are changing value of out
It should be able to hold value):
reg out;
out = a & b;

*/

// Customisation 

/*
THe gtkwave shoed waveforms in tho order:
A
B
Borrow
Difference

I wanted it show in this order:
A
B
Difference
Borrow

So i needed to know what does that depend on (the order in which we declare ports?
or the order in which they are output-ed)
Turned out it was the latter.
*/

FSM_Implementation_Verilog/Verilog_Project/xyz.vcd
$date
	Fri Feb 17 00:00:33 2023
$end
$version
	Icarus Verilog
$end
$timescale
	1ps
$end
$scope module top $end
$var wire 1 ! Difference $end
$var wire 1 " Borrow $end
$var reg 1 # A $end
$var reg 1 $ B $end
$scope module instantiation $end
$var wire 1 # a $end
$var wire 1 $ b $end
$var wire 1 % x $end
$var wire 1 ! difference $end
$var wire 1 " borrow $end
$scope module and_gate_in_half_sub $end
$var wire 1 $ b $end
$var wire 1 " out $end
$var wire 1 % a $end
$upscope $end
$scope module not_gate_in_half_sub $end
$var wire 1 # a $end
$var wire 1 % out $end
$upscope $end
$scope module xor_gate_in_half_sub $end
$var wire 1 # a $end
$var wire 1 $ b $end
$var wire 1 ! out $end
$upscope $end
$upscope $end
$upscope $end
$enddefinitions $end
$comment Show the parameter values. $end
$dumpall
$end
#0
$dumpvars
1%
0$
0#
0"
0!
$end
#5000
1!
1"
1$
#10000
0"
0%
0$
1#
#15000
0!
1$
#20000
1%
0$
0#
#25000
1!
1"
1$
#30000
0"
0%
0$
1#
#35000
0!
1$
#40000
1%
0$
0#
#45000
1!
1"
1$
#50000
0"
0%
0$
1#
#55000
0!
1$
#60000
1%
0$
0#
#65000
1!
1"
1$
#70000
0"
0%
0$
1#
#75000
0!
1$
#80000
1%
0$
0#
#85000
1!
1"
1$
#90000
0"
0%
0$
1#
#95000
0!
1$
#100000
1%
0$
0#
