FSM_Implementation_Verilog/Theory and Examples/Practise/first.v
// module name can't begin with a number , 2_1_mux is invalid module name
module structure_mux(in0,in1,select_line,out);

input in0 , in1 , select_line;
output out;
wire not_select_line,o1,o2;

not not1(not_select_line,select_line);
and and1(o1,in0,not_select_line);
and and2(o2,in1,select_line);
or final_or(out,o1,o2);
    
endmodule

FSM_Implementation_Verilog/Theory and Examples/Practise/first_tb.v
//So the time unit is 1ns and whenever we encounter #10 it is 10*1ns = 1ns delay
`timescale 1ns/1ps
// Since I was getting `bash: ./a.out: /c/Source/iverilog-install/bin/vvp^M: bad interpreter: No such file or directory` 
// error shown whenver I try to execute ./a.out ,I had to get the .vcd file synthesised in some other way
// As I understand I had to use these vvp commands
`include "first.v"


// use - instead of _ , it's easier to ctrl move and del and stuff
module first_tb;

reg Data_for_in0;
reg Data_for_in1;
reg Data_for_select_line;

wire Data_for_out;;

// Creating an instance of the module 
structure_mux mux_component(Data_for_in0,Data_for_in1,Data_for_select_line,Data_for_out);

initial begin

    //
    $dumpfile("first_out.vcd");
    // starting from t=0 the module first_tb is dumped
    $dumpvars(0,first_tb);


    Data_for_in0 = 0;  Data_for_in1 = 0;  Data_for_select_line = 0;  #50;
    Data_for_in0 = 0;  Data_for_in1 = 0;  Data_for_select_line = 1;  #10;
    Data_for_in0 = 0;  Data_for_in1 = 1;  Data_for_select_line = 0;  #10;
    Data_for_in0 = 0;  Data_for_in1 = 1;  Data_for_select_line = 1;  #10;
    Data_for_in0 = 1;  Data_for_in1 = 0;  Data_for_select_line = 0;  #10;
    Data_for_in0 = 1;  Data_for_in1 = 0;  Data_for_select_line = 1;  #10;
    Data_for_in0 = 1;  Data_for_in1 = 1;  Data_for_select_line = 0;  #10;
    Data_for_in0 = 1;  Data_for_in1 = 1;  Data_for_select_line = 1;  #10;
end
    
endmodule

FSM_Implementation_Verilog/Theory and Examples/Practise/first_out.vcd
$date
	Wed Feb 15 21:08:53 2023
$end
$version
	Icarus Verilog
$end
$timescale
	1ps
$end
$scope module first_tb $end
$var wire 1 ! Data_for_out $end
$var reg 1 " Data_for_in0 $end
$var reg 1 # Data_for_in1 $end
$var reg 1 $ Data_for_select_line $end
$scope module mux_component $end
$var wire 1 " in0 $end
$var wire 1 # in1 $end
$var wire 1 % not_select_line $end
$var wire 1 & o1 $end
$var wire 1 ' o2 $end
$var wire 1 ! out $end
$var wire 1 $ select_line $end
$upscope $end
$upscope $end
$enddefinitions $end
$comment Show the parameter values. $end
$dumpall
$end
#0
$dumpvars
0'
0&
1%
0$
0#
0"
0!
$end
#50000
0%
1$
#60000
1%
0$
1#
#70000
1!
0%
1'
1$
#80000
1&
1!
1%
0'
0$
0#
1"
#90000
0!
0&
0%
1$
#100000
1!
1&
1%
0$
1#
#110000
0&
0%
1'
1$
